{
   "for_annual" : {
      "imo_dcs" : [
         {
            "arr_port_display" : {
               "format" : {
                  "init_val" : "---",
                  "datetime" : "",
                  "round" : ""
               },
               "type" : "none"
            }
         },
         {
            "eu_mrv_display" : {
               "format" : {
                  "round" : "",
                  "datetime" : "",
                  "init_val" : "---"
               },
               "type" : "none"
            }
         },
         {
            "passenger" : {
               "type" : "none",
               "format" : {
                  "round" : "",
                  "datetime" : "",
                  "init_val" : "---"
               }
            }
         },
         {
            "unit_empty" : {
               "format" : {
                  "round" : "",
                  "datetime" : "",
                  "init_val" : "---"
               },
               "type" : "none"
            }
         },
         {
            "foc_lfo_per_distance" : {
               "type" : "none",
               "format" : {
                  "round" : "",
                  "datetime" : "",
                  "init_val" : "---"
               }
            }
         },
         {
            "foc_other_per_transport_work" : {
               "format" : {
                  "init_val" : "---",
                  "round" : "",
                  "datetime" : ""
               },
               "type" : "none"
            }
         },
         {
            "unit_laden" : {
               "type" : "none",
               "format" : {
                  "round" : "",
                  "datetime" : "",
                  "init_val" : "---"
               }
            }
         },
         {
            "dep_port" : {
               "format" : {
                  "round" : "",
                  "datetime" : "",
                  "init_val" : "---"
               },
               "type" : "none"
            }
         },
         {
            "time_at_sea" : {
               "type" : "none",
               "format" : {
                  "init_val" : "---",
                  "round" : "",
                  "datetime" : ""
               }
            }
         },
         {
            "foc_other_per_distance" : {
               "type" : "none",
               "format" : {
                  "datetime" : "",
                  "round" : "",
                  "init_val" : "---"
               }
            }
         },
         {
            "arr_date_time" : {
               "format" : {
                  "init_val" : "---",
                  "round" : "",
                  "datetime" : "%m/%d %H:%M"
               },
               "type" : "none"
            }
         },
         {
            "dwt_carried" : {
               "format" : {
                  "init_val" : "---",
                  "round" : "",
                  "datetime" : ""
               },
               "type" : "none"
            }
         },
         {
            "foc_hfo_per_distance" : {
               "format" : {
                  "init_val" : "---",
                  "round" : "",
                  "datetime" : ""
               },
               "type" : "none"
            }
         },
         {
            "cars" : {
               "format" : {
                  "round" : "",
                  "datetime" : "",
                  "init_val" : "---"
               },
               "type" : "none"
            }
         },
         {
            "hours_underway" : {
               "format" : {
                  "datetime" : "",
                  "round" : "1",
                  "init_val" : ""
               },
               "threshold" : {
                  "min" : "0.0",
                  "max" : "9999.9"
               },
               "type" : "none"
            }
         },
         {
            "eeoi" : {
               "format" : {
                  "init_val" : "---",
                  "datetime" : "",
                  "round" : ""
               },
               "type" : "none"
            }
         },
         {
            "foc_dogo_per_transport_work" : {
               "format" : {
                  "round" : "",
                  "datetime" : "",
                  "init_val" : "---"
               },
               "type" : "none"
            }
         },
         {
            "volume" : {
               "type" : "none",
               "format" : {
                  "round" : "",
                  "datetime" : "",
                  "init_val" : "---"
               }
            }
         },
         {
            "eu_mrv" : {
               "format" : {
                  "datetime" : "",
                  "round" : "",
                  "init_val" : "---"
               },
               "type" : "none"
            }
         },
         {
            "foc_lfo_per_transport_work" : {
               "type" : "none",
               "format" : {
                  "round" : "",
                  "datetime" : "",
                  "init_val" : "---"
               }
            }
         },
         {
            "cargo_weight" : {
               "type" : "none",
               "format" : {
                  "datetime" : "",
                  "round" : "",
                  "init_val" : "---"
               }
            }
         },
         {
            "foc_lfo" : {
               "format" : {
                  "init_val" : "***",
                  "round" : "2",
                  "datetime" : ""
               },
               "threshold" : {
                  "max" : "99999.99",
                  "min" : "0.00"
               },
               "type" : "none"
            }
         },
         {
            "dep_date_time" : {
               "format" : {
                  "round" : "",
                  "datetime" : "%m/%d %H:%M",
                  "init_val" : "---"
               },
               "type" : "none"
            }
         },
         {
            "distance_travelled" : {
               "type" : "none",
               "threshold" : {
                  "min" : "0",
                  "max" : "99999"
               },
               "format" : {
                  "round" : "0",
                  "datetime" : "",
                  "init_val" : ""
               }
            }
         },
         {
            "co2_other" : {
               "type" : "none",
               "format" : {
                  "datetime" : "",
                  "round" : "2",
                  "init_val" : ""
               },
               "threshold" : {
                  "min" : "0.00",
                  "max" : "999999.99"
               }
            }
         },
         {
            "co2_dogo" : {
               "format" : {
                  "round" : "2",
                  "datetime" : "",
                  "init_val" : "***"
               },
               "threshold" : {
                  "min" : "0.00",
                  "max" : "999999.99"
               },
               "type" : "none"
            }
         },
         {
            "co2_hfo" : {
               "format" : {
                  "datetime" : "",
                  "round" : "2",
                  "init_val" : "***"
               },
               "threshold" : {
                  "max" : "999999.99",
                  "min" : "0.00"
               },
               "type" : "none"
            }
         },
         {
            "dep_port_display" : {
               "format" : {
                  "round" : "",
                  "datetime" : "",
                  "init_val" : "---"
               },
               "type" : "none"
            }
         },
         {
            "voyage_number" : {
               "format" : {
                  "datetime" : "",
                  "round" : "",
                  "init_val" : "---"
               },
               "type" : "none"
            }
         },
         {
            "transport_work" : {
               "format" : {
                  "round" : "",
                  "datetime" : "",
                  "init_val" : "---"
               },
               "type" : "none"
            }
         },
         {
            "co2_lfo" : {
               "type" : "none",
               "format" : {
                  "init_val" : "***",
                  "round" : "2",
                  "datetime" : ""
               },
               "threshold" : {
                  "max" : "999999.99",
                  "min" : "0.00"
               }
            }
         },
         {
            "co2_per_distance" : {
               "type" : "none",
               "format" : {
                  "datetime" : "",
                  "round" : "",
                  "init_val" : "---"
               }
            }
         },
         {
            "foc_dogo_per_distance" : {
               "type" : "none",
               "format" : {
                  "round" : "",
                  "datetime" : "",
                  "init_val" : "---"
               }
            }
         },
         {
            "foc_dogo" : {
               "threshold" : {
                  "min" : "0.00",
                  "max" : "99999.99"
               },
               "format" : {
                  "datetime" : "",
                  "round" : "2",
                  "init_val" : "***"
               },
               "type" : "none"
            }
         },
         {
            "foc_hfo_per_transport_work" : {
               "type" : "none",
               "format" : {
                  "init_val" : "---",
                  "datetime" : "",
                  "round" : ""
               }
            }
         },
         {
            "arr_port" : {
               "type" : "none",
               "format" : {
                  "init_val" : "---",
                  "round" : "",
                  "datetime" : ""
               }
            }
         },
         {
            "foc_other" : {
               "threshold" : {
                  "max" : "99999.99",
                  "min" : "0.00"
               },
               "format" : {
                  "datetime" : "",
                  "round" : "2",
                  "init_val" : ""
               },
               "type" : "none"
            }
         },
         {
            "foc_hfo" : {
               "type" : "none",
               "threshold" : {
                  "min" : "0.00",
                  "max" : "99999.99"
               },
               "format" : {
                  "init_val" : "***",
                  "round" : "2",
                  "datetime" : ""
               }
            }
         }
      ]
   }
}
